SIMHousing4DG/__init__.py
SIMHousing4DG/__main__.py
SIMHousing4DG/launch.py
SIMHousing4DG/fonts/NotoSerifCJKsc-Black.otf
simhousing4dg-0.1.0.dist-info/METADATA
simhousing4dg-0.1.0.dist-info/WHEEL
simhousing4dg-0.1.0.dist-info/entry_points.txt
simhousing4dg-0.1.0.dist-info/top_level.txt
simhousing4dg-0.1.0.dist-info/RECORD
